pretext_match/__init__.py
pretext_match/pretext_match.py
pretext_match/test_pretext_match.py
pretextmatch-0.0.1.dist-info/METADATA
pretextmatch-0.0.1.dist-info/RECORD
pretextmatch-0.0.1.dist-info/WHEEL
pretextmatch-0.0.1.dist-info/top_level.txt
