Metadata-Version: 2.1
Name: pretextmatch
Version: 0.0.1
Summary: Complex text matching, simply
Home-page: https://github.com/dubyuhtee/pretext_matcher
Author: William Hanson
Author-email: dubyuhtee@gmail.com
License: UNKNOWN
Platform: UNKNOWN
Classifier: Programming Language :: Python :: 3
Classifier: License :: OSI Approved :: MIT License
Classifier: Operating System :: OS Independent
Classifier: Development Status :: 4 - Beta
